setup.py
encrypedloader/__init__.py
encrypedloader/encrypedloader.py
encrypedloader/loader.c
encrypedloader.egg-info/PKG-INFO
encrypedloader.egg-info/SOURCES.txt
encrypedloader.egg-info/dependency_links.txt
encrypedloader.egg-info/entry_points.txt
encrypedloader.egg-info/requires.txt
encrypedloader.egg-info/top_level.txt
encrypedloader.egg-info/zip-safe